{
  "version": "5",
  "dialect": "mysql",
  "id": "5c76dcc0-fce9-4951-b6bf-7d96cf461bca",
  "prevId": "3d550ec9-d148-47e4-a022-b361bd16633e",
  "tables": {
    "catalog_categories": {
      "name": "catalog_categories",
      "columns": {
        "id": {
          "name": "id",
          "type": "int",
          "primaryKey": false,
          "notNull": true,
          "autoincrement": true
        },
        "slug": {
          "name": "slug",
          "type": "varchar(100)",
          "primaryKey": false,
          "notNull": true,
          "autoincrement": false
        },
        "name": {
          "name": "name",
          "type": "varchar(255)",
          "primaryKey": false,
          "notNull": true,
          "autoincrement": false
        },
        "description": {
          "name": "description",
          "type": "text",
          "primaryKey": false,
          "notNull": false,
          "autoincrement": false
        },
        "product_count": {
          "name": "product_count",
          "type": "int",
          "primaryKey": false,
          "notNull": true,
          "autoincrement": false,
          "default": 0
        },
        "design_level": {
          "name": "design_level",
          "type": "enum('low','medium','high')",
          "primaryKey": false,
          "notNull": true,
          "autoincrement": false,
          "default": "'medium'"
        },
        "service_type": {
          "name": "service_type",
          "type": "varchar(255)",
          "primaryKey": false,
          "notNull": false,
          "autoincrement": false
        },
        "image_url": {
          "name": "image_url",
          "type": "varchar(500)",
          "primaryKey": false,
          "notNull": false,
          "autoincrement": false
        },
        "display_order": {
          "name": "display_order",
          "type": "int",
          "primaryKey": false,
          "notNull": true,
          "autoincrement": false,
          "default": 0
        },
        "is_active": {
          "name": "is_active",
          "type": "int",
          "primaryKey": false,
          "notNull": true,
          "autoincrement": false,
          "default": 1
        },
        "created_at": {
          "name": "created_at",
          "type": "timestamp",
          "primaryKey": false,
          "notNull": true,
          "autoincrement": false,
          "default": "(now())"
        },
        "updated_at": {
          "name": "updated_at",
          "type": "timestamp",
          "primaryKey": false,
          "notNull": true,
          "autoincrement": false,
          "onUpdate": true,
          "default": "(now())"
        }
      },
      "indexes": {},
      "foreignKeys": {},
      "compositePrimaryKeys": {
        "catalog_categories_id": {
          "name": "catalog_categories_id",
          "columns": [
            "id"
          ]
        }
      },
      "uniqueConstraints": {
        "catalog_categories_slug_unique": {
          "name": "catalog_categories_slug_unique",
          "columns": [
            "slug"
          ]
        }
      },
      "checkConstraint": {}
    },
    "catalog_products": {
      "name": "catalog_products",
      "columns": {
        "id": {
          "name": "id",
          "type": "int",
          "primaryKey": false,
          "notNull": true,
          "autoincrement": true
        },
        "category_id": {
          "name": "category_id",
          "type": "int",
          "primaryKey": false,
          "notNull": true,
          "autoincrement": false
        },
        "subcategory_id": {
          "name": "subcategory_id",
          "type": "int",
          "primaryKey": false,
          "notNull": false,
          "autoincrement": false
        },
        "jds_sku": {
          "name": "jds_sku",
          "type": "varchar(50)",
          "primaryKey": false,
          "notNull": true,
          "autoincrement": false
        },
        "jds_class_code": {
          "name": "jds_class_code",
          "type": "varchar(50)",
          "primaryKey": false,
          "notNull": false,
          "autoincrement": false
        },
        "name": {
          "name": "name",
          "type": "varchar(500)",
          "primaryKey": false,
          "notNull": true,
          "autoincrement": false
        },
        "description": {
          "name": "description",
          "type": "text",
          "primaryKey": false,
          "notNull": false,
          "autoincrement": false
        },
        "description_long": {
          "name": "description_long",
          "type": "text",
          "primaryKey": false,
          "notNull": false,
          "autoincrement": false
        },
        "wholesale_price": {
          "name": "wholesale_price",
          "type": "int",
          "primaryKey": false,
          "notNull": false,
          "autoincrement": false
        },
        "retail_price": {
          "name": "retail_price",
          "type": "int",
          "primaryKey": false,
          "notNull": false,
          "autoincrement": false
        },
        "dimensions": {
          "name": "dimensions",
          "type": "varchar(255)",
          "primaryKey": false,
          "notNull": false,
          "autoincrement": false
        },
        "weight": {
          "name": "weight",
          "type": "varchar(100)",
          "primaryKey": false,
          "notNull": false,
          "autoincrement": false
        },
        "material": {
          "name": "material",
          "type": "varchar(255)",
          "primaryKey": false,
          "notNull": false,
          "autoincrement": false
        },
        "color": {
          "name": "color",
          "type": "varchar(100)",
          "primaryKey": false,
          "notNull": false,
          "autoincrement": false
        },
        "image_url": {
          "name": "image_url",
          "type": "varchar(500)",
          "primaryKey": false,
          "notNull": false,
          "autoincrement": false
        },
        "thumbnail_url": {
          "name": "thumbnail_url",
          "type": "varchar(500)",
          "primaryKey": false,
          "notNull": false,
          "autoincrement": false
        },
        "additional_images": {
          "name": "additional_images",
          "type": "text",
          "primaryKey": false,
          "notNull": false,
          "autoincrement": false
        },
        "keywords": {
          "name": "keywords",
          "type": "text",
          "primaryKey": false,
          "notNull": false,
          "autoincrement": false
        },
        "search_text": {
          "name": "search_text",
          "type": "text",
          "primaryKey": false,
          "notNull": false,
          "autoincrement": false
        },
        "in_stock": {
          "name": "in_stock",
          "type": "int",
          "primaryKey": false,
          "notNull": true,
          "autoincrement": false,
          "default": 1
        },
        "min_order_qty": {
          "name": "min_order_qty",
          "type": "int",
          "primaryKey": false,
          "notNull": true,
          "autoincrement": false,
          "default": 1
        },
        "design_level": {
          "name": "design_level",
          "type": "enum('low','medium','high')",
          "primaryKey": false,
          "notNull": true,
          "autoincrement": false,
          "default": "'medium'"
        },
        "customization_options": {
          "name": "customization_options",
          "type": "text",
          "primaryKey": false,
          "notNull": false,
          "autoincrement": false
        },
        "is_featured": {
          "name": "is_featured",
          "type": "int",
          "primaryKey": false,
          "notNull": true,
          "autoincrement": false,
          "default": 0
        },
        "is_active": {
          "name": "is_active",
          "type": "int",
          "primaryKey": false,
          "notNull": true,
          "autoincrement": false,
          "default": 1
        },
        "display_order": {
          "name": "display_order",
          "type": "int",
          "primaryKey": false,
          "notNull": true,
          "autoincrement": false,
          "default": 0
        },
        "created_at": {
          "name": "created_at",
          "type": "timestamp",
          "primaryKey": false,
          "notNull": true,
          "autoincrement": false,
          "default": "(now())"
        },
        "updated_at": {
          "name": "updated_at",
          "type": "timestamp",
          "primaryKey": false,
          "notNull": true,
          "autoincrement": false,
          "onUpdate": true,
          "default": "(now())"
        }
      },
      "indexes": {},
      "foreignKeys": {
        "catalog_products_category_id_catalog_categories_id_fk": {
          "name": "catalog_products_category_id_catalog_categories_id_fk",
          "tableFrom": "catalog_products",
          "tableTo": "catalog_categories",
          "columnsFrom": [
            "category_id"
          ],
          "columnsTo": [
            "id"
          ],
          "onDelete": "no action",
          "onUpdate": "no action"
        },
        "catalog_products_subcategory_id_catalog_subcategories_id_fk": {
          "name": "catalog_products_subcategory_id_catalog_subcategories_id_fk",
          "tableFrom": "catalog_products",
          "tableTo": "catalog_subcategories",
          "columnsFrom": [
            "subcategory_id"
          ],
          "columnsTo": [
            "id"
          ],
          "onDelete": "no action",
          "onUpdate": "no action"
        }
      },
      "compositePrimaryKeys": {
        "catalog_products_id": {
          "name": "catalog_products_id",
          "columns": [
            "id"
          ]
        }
      },
      "uniqueConstraints": {
        "catalog_products_jds_sku_unique": {
          "name": "catalog_products_jds_sku_unique",
          "columns": [
            "jds_sku"
          ]
        }
      },
      "checkConstraint": {}
    },
    "catalog_subcategories": {
      "name": "catalog_subcategories",
      "columns": {
        "id": {
          "name": "id",
          "type": "int",
          "primaryKey": false,
          "notNull": true,
          "autoincrement": true
        },
        "category_id": {
          "name": "category_id",
          "type": "int",
          "primaryKey": false,
          "notNull": true,
          "autoincrement": false
        },
        "jds_class_code": {
          "name": "jds_class_code",
          "type": "varchar(50)",
          "primaryKey": false,
          "notNull": false,
          "autoincrement": false
        },
        "slug": {
          "name": "slug",
          "type": "varchar(100)",
          "primaryKey": false,
          "notNull": true,
          "autoincrement": false
        },
        "name": {
          "name": "name",
          "type": "varchar(255)",
          "primaryKey": false,
          "notNull": true,
          "autoincrement": false
        },
        "description": {
          "name": "description",
          "type": "text",
          "primaryKey": false,
          "notNull": false,
          "autoincrement": false
        },
        "product_count": {
          "name": "product_count",
          "type": "int",
          "primaryKey": false,
          "notNull": true,
          "autoincrement": false,
          "default": 0
        },
        "image_url": {
          "name": "image_url",
          "type": "varchar(500)",
          "primaryKey": false,
          "notNull": false,
          "autoincrement": false
        },
        "display_order": {
          "name": "display_order",
          "type": "int",
          "primaryKey": false,
          "notNull": true,
          "autoincrement": false,
          "default": 0
        },
        "is_active": {
          "name": "is_active",
          "type": "int",
          "primaryKey": false,
          "notNull": true,
          "autoincrement": false,
          "default": 1
        },
        "created_at": {
          "name": "created_at",
          "type": "timestamp",
          "primaryKey": false,
          "notNull": true,
          "autoincrement": false,
          "default": "(now())"
        }
      },
      "indexes": {},
      "foreignKeys": {
        "catalog_subcategories_category_id_catalog_categories_id_fk": {
          "name": "catalog_subcategories_category_id_catalog_categories_id_fk",
          "tableFrom": "catalog_subcategories",
          "tableTo": "catalog_categories",
          "columnsFrom": [
            "category_id"
          ],
          "columnsTo": [
            "id"
          ],
          "onDelete": "cascade",
          "onUpdate": "no action"
        }
      },
      "compositePrimaryKeys": {
        "catalog_subcategories_id": {
          "name": "catalog_subcategories_id",
          "columns": [
            "id"
          ]
        }
      },
      "uniqueConstraints": {},
      "checkConstraint": {}
    },
    "designs": {
      "name": "designs",
      "columns": {
        "id": {
          "name": "id",
          "type": "int",
          "primaryKey": false,
          "notNull": true,
          "autoincrement": true
        },
        "projectId": {
          "name": "projectId",
          "type": "int",
          "primaryKey": false,
          "notNull": true,
          "autoincrement": false
        },
        "designTheme": {
          "name": "designTheme",
          "type": "text",
          "primaryKey": false,
          "notNull": false,
          "autoincrement": false
        },
        "mockupUrl": {
          "name": "mockupUrl",
          "type": "varchar(500)",
          "primaryKey": false,
          "notNull": false,
          "autoincrement": false
        },
        "iconsFonts": {
          "name": "iconsFonts",
          "type": "text",
          "primaryKey": false,
          "notNull": false,
          "autoincrement": false
        },
        "designNotes": {
          "name": "designNotes",
          "type": "text",
          "primaryKey": false,
          "notNull": false,
          "autoincrement": false
        },
        "revisionNumber": {
          "name": "revisionNumber",
          "type": "int",
          "primaryKey": false,
          "notNull": true,
          "autoincrement": false,
          "default": 1
        },
        "status": {
          "name": "status",
          "type": "enum('draft','submitted','approved','revision_requested')",
          "primaryKey": false,
          "notNull": true,
          "autoincrement": false,
          "default": "'draft'"
        },
        "createdAt": {
          "name": "createdAt",
          "type": "timestamp",
          "primaryKey": false,
          "notNull": true,
          "autoincrement": false,
          "default": "(now())"
        },
        "updatedAt": {
          "name": "updatedAt",
          "type": "timestamp",
          "primaryKey": false,
          "notNull": true,
          "autoincrement": false,
          "onUpdate": true,
          "default": "(now())"
        }
      },
      "indexes": {},
      "foreignKeys": {},
      "compositePrimaryKeys": {
        "designs_id": {
          "name": "designs_id",
          "columns": [
            "id"
          ]
        }
      },
      "uniqueConstraints": {},
      "checkConstraint": {}
    },
    "fulfillments": {
      "name": "fulfillments",
      "columns": {
        "id": {
          "name": "id",
          "type": "int",
          "primaryKey": false,
          "notNull": true,
          "autoincrement": true
        },
        "projectId": {
          "name": "projectId",
          "type": "int",
          "primaryKey": false,
          "notNull": true,
          "autoincrement": false
        },
        "thankYouMessage": {
          "name": "thankYouMessage",
          "type": "text",
          "primaryKey": false,
          "notNull": false,
          "autoincrement": false
        },
        "careInstructions": {
          "name": "careInstructions",
          "type": "text",
          "primaryKey": false,
          "notNull": false,
          "autoincrement": false
        },
        "packagingNotes": {
          "name": "packagingNotes",
          "type": "text",
          "primaryKey": false,
          "notNull": false,
          "autoincrement": false
        },
        "shippingMethod": {
          "name": "shippingMethod",
          "type": "varchar(100)",
          "primaryKey": false,
          "notNull": false,
          "autoincrement": false
        },
        "trackingNumber": {
          "name": "trackingNumber",
          "type": "varchar(255)",
          "primaryKey": false,
          "notNull": false,
          "autoincrement": false
        },
        "shippedDate": {
          "name": "shippedDate",
          "type": "timestamp",
          "primaryKey": false,
          "notNull": false,
          "autoincrement": false
        },
        "deliveredDate": {
          "name": "deliveredDate",
          "type": "timestamp",
          "primaryKey": false,
          "notNull": false,
          "autoincrement": false
        },
        "createdAt": {
          "name": "createdAt",
          "type": "timestamp",
          "primaryKey": false,
          "notNull": true,
          "autoincrement": false,
          "default": "(now())"
        },
        "updatedAt": {
          "name": "updatedAt",
          "type": "timestamp",
          "primaryKey": false,
          "notNull": true,
          "autoincrement": false,
          "onUpdate": true,
          "default": "(now())"
        }
      },
      "indexes": {},
      "foreignKeys": {},
      "compositePrimaryKeys": {
        "fulfillments_id": {
          "name": "fulfillments_id",
          "columns": [
            "id"
          ]
        }
      },
      "uniqueConstraints": {},
      "checkConstraint": {}
    },
    "intake_attachments": {
      "name": "intake_attachments",
      "columns": {
        "id": {
          "name": "id",
          "type": "int",
          "primaryKey": false,
          "notNull": true,
          "autoincrement": true
        },
        "intake_id": {
          "name": "intake_id",
          "type": "int",
          "primaryKey": false,
          "notNull": true,
          "autoincrement": false
        },
        "file_url": {
          "name": "file_url",
          "type": "text",
          "primaryKey": false,
          "notNull": true,
          "autoincrement": false
        },
        "file_key": {
          "name": "file_key",
          "type": "text",
          "primaryKey": false,
          "notNull": true,
          "autoincrement": false
        },
        "file_name": {
          "name": "file_name",
          "type": "varchar(255)",
          "primaryKey": false,
          "notNull": true,
          "autoincrement": false
        },
        "file_size": {
          "name": "file_size",
          "type": "int",
          "primaryKey": false,
          "notNull": true,
          "autoincrement": false
        },
        "mime_type": {
          "name": "mime_type",
          "type": "varchar(100)",
          "primaryKey": false,
          "notNull": false,
          "autoincrement": false
        },
        "created_at": {
          "name": "created_at",
          "type": "timestamp",
          "primaryKey": false,
          "notNull": true,
          "autoincrement": false,
          "default": "(now())"
        }
      },
      "indexes": {},
      "foreignKeys": {
        "intake_attachments_intake_id_intakeForms_id_fk": {
          "name": "intake_attachments_intake_id_intakeForms_id_fk",
          "tableFrom": "intake_attachments",
          "tableTo": "intakeForms",
          "columnsFrom": [
            "intake_id"
          ],
          "columnsTo": [
            "id"
          ],
          "onDelete": "cascade",
          "onUpdate": "no action"
        }
      },
      "compositePrimaryKeys": {
        "intake_attachments_id": {
          "name": "intake_attachments_id",
          "columns": [
            "id"
          ]
        }
      },
      "uniqueConstraints": {},
      "checkConstraint": {}
    },
    "intakeForms": {
      "name": "intakeForms",
      "columns": {
        "id": {
          "name": "id",
          "type": "int",
          "primaryKey": false,
          "notNull": true,
          "autoincrement": true
        },
        "projectId": {
          "name": "projectId",
          "type": "int",
          "primaryKey": false,
          "notNull": true,
          "autoincrement": false
        },
        "rawMessage": {
          "name": "rawMessage",
          "type": "text",
          "primaryKey": false,
          "notNull": true,
          "autoincrement": false
        },
        "projectType": {
          "name": "projectType",
          "type": "varchar(100)",
          "primaryKey": false,
          "notNull": false,
          "autoincrement": false
        },
        "material": {
          "name": "material",
          "type": "varchar(100)",
          "primaryKey": false,
          "notNull": false,
          "autoincrement": false
        },
        "dimensions": {
          "name": "dimensions",
          "type": "varchar(255)",
          "primaryKey": false,
          "notNull": false,
          "autoincrement": false
        },
        "quantity": {
          "name": "quantity",
          "type": "int",
          "primaryKey": false,
          "notNull": false,
          "autoincrement": false
        },
        "deadline": {
          "name": "deadline",
          "type": "timestamp",
          "primaryKey": false,
          "notNull": false,
          "autoincrement": false
        },
        "budget": {
          "name": "budget",
          "type": "varchar(100)",
          "primaryKey": false,
          "notNull": false,
          "autoincrement": false
        },
        "specialRequirements": {
          "name": "specialRequirements",
          "type": "text",
          "primaryKey": false,
          "notNull": false,
          "autoincrement": false
        },
        "createdAt": {
          "name": "createdAt",
          "type": "timestamp",
          "primaryKey": false,
          "notNull": true,
          "autoincrement": false,
          "default": "(now())"
        }
      },
      "indexes": {},
      "foreignKeys": {},
      "compositePrimaryKeys": {
        "intakeForms_id": {
          "name": "intakeForms_id",
          "columns": [
            "id"
          ]
        }
      },
      "uniqueConstraints": {},
      "checkConstraint": {}
    },
    "message_attachments": {
      "name": "message_attachments",
      "columns": {
        "id": {
          "name": "id",
          "type": "int",
          "primaryKey": false,
          "notNull": true,
          "autoincrement": true
        },
        "message_id": {
          "name": "message_id",
          "type": "int",
          "primaryKey": false,
          "notNull": true,
          "autoincrement": false
        },
        "file_name": {
          "name": "file_name",
          "type": "varchar(255)",
          "primaryKey": false,
          "notNull": true,
          "autoincrement": false
        },
        "file_url": {
          "name": "file_url",
          "type": "varchar(500)",
          "primaryKey": false,
          "notNull": true,
          "autoincrement": false
        },
        "file_type": {
          "name": "file_type",
          "type": "varchar(100)",
          "primaryKey": false,
          "notNull": false,
          "autoincrement": false
        },
        "file_size": {
          "name": "file_size",
          "type": "int",
          "primaryKey": false,
          "notNull": false,
          "autoincrement": false
        },
        "created_at": {
          "name": "created_at",
          "type": "timestamp",
          "primaryKey": false,
          "notNull": true,
          "autoincrement": false,
          "default": "(now())"
        }
      },
      "indexes": {},
      "foreignKeys": {
        "message_attachments_message_id_project_messages_id_fk": {
          "name": "message_attachments_message_id_project_messages_id_fk",
          "tableFrom": "message_attachments",
          "tableTo": "project_messages",
          "columnsFrom": [
            "message_id"
          ],
          "columnsTo": [
            "id"
          ],
          "onDelete": "cascade",
          "onUpdate": "no action"
        }
      },
      "compositePrimaryKeys": {
        "message_attachments_id": {
          "name": "message_attachments_id",
          "columns": [
            "id"
          ]
        }
      },
      "uniqueConstraints": {},
      "checkConstraint": {}
    },
    "order_items": {
      "name": "order_items",
      "columns": {
        "id": {
          "name": "id",
          "type": "int",
          "primaryKey": false,
          "notNull": true,
          "autoincrement": true
        },
        "order_id": {
          "name": "order_id",
          "type": "int",
          "primaryKey": false,
          "notNull": true,
          "autoincrement": false
        },
        "product_id": {
          "name": "product_id",
          "type": "varchar(100)",
          "primaryKey": false,
          "notNull": true,
          "autoincrement": false
        },
        "product_name": {
          "name": "product_name",
          "type": "varchar(255)",
          "primaryKey": false,
          "notNull": true,
          "autoincrement": false
        },
        "description": {
          "name": "description",
          "type": "text",
          "primaryKey": false,
          "notNull": false,
          "autoincrement": false
        },
        "quantity": {
          "name": "quantity",
          "type": "int",
          "primaryKey": false,
          "notNull": true,
          "autoincrement": false,
          "default": 1
        },
        "unit_price": {
          "name": "unit_price",
          "type": "int",
          "primaryKey": false,
          "notNull": true,
          "autoincrement": false
        },
        "total": {
          "name": "total",
          "type": "int",
          "primaryKey": false,
          "notNull": true,
          "autoincrement": false
        },
        "created_at": {
          "name": "created_at",
          "type": "timestamp",
          "primaryKey": false,
          "notNull": true,
          "autoincrement": false,
          "default": "(now())"
        }
      },
      "indexes": {},
      "foreignKeys": {
        "order_items_order_id_orders_id_fk": {
          "name": "order_items_order_id_orders_id_fk",
          "tableFrom": "order_items",
          "tableTo": "orders",
          "columnsFrom": [
            "order_id"
          ],
          "columnsTo": [
            "id"
          ],
          "onDelete": "cascade",
          "onUpdate": "no action"
        }
      },
      "compositePrimaryKeys": {
        "order_items_id": {
          "name": "order_items_id",
          "columns": [
            "id"
          ]
        }
      },
      "uniqueConstraints": {},
      "checkConstraint": {}
    },
    "orders": {
      "name": "orders",
      "columns": {
        "id": {
          "name": "id",
          "type": "int",
          "primaryKey": false,
          "notNull": true,
          "autoincrement": true
        },
        "order_number": {
          "name": "order_number",
          "type": "varchar(50)",
          "primaryKey": false,
          "notNull": true,
          "autoincrement": false
        },
        "invoice_number": {
          "name": "invoice_number",
          "type": "varchar(50)",
          "primaryKey": false,
          "notNull": true,
          "autoincrement": false
        },
        "user_id": {
          "name": "user_id",
          "type": "int",
          "primaryKey": false,
          "notNull": false,
          "autoincrement": false
        },
        "project_id": {
          "name": "project_id",
          "type": "int",
          "primaryKey": false,
          "notNull": false,
          "autoincrement": false
        },
        "customer_name": {
          "name": "customer_name",
          "type": "varchar(255)",
          "primaryKey": false,
          "notNull": true,
          "autoincrement": false
        },
        "customer_email": {
          "name": "customer_email",
          "type": "varchar(320)",
          "primaryKey": false,
          "notNull": true,
          "autoincrement": false
        },
        "order_type": {
          "name": "order_type",
          "type": "enum('product','deposit','balance')",
          "primaryKey": false,
          "notNull": true,
          "autoincrement": false
        },
        "status": {
          "name": "status",
          "type": "enum('pending','paid','failed','refunded')",
          "primaryKey": false,
          "notNull": true,
          "autoincrement": false,
          "default": "'pending'"
        },
        "subtotal": {
          "name": "subtotal",
          "type": "int",
          "primaryKey": false,
          "notNull": true,
          "autoincrement": false
        },
        "tax": {
          "name": "tax",
          "type": "int",
          "primaryKey": false,
          "notNull": true,
          "autoincrement": false,
          "default": 0
        },
        "total": {
          "name": "total",
          "type": "int",
          "primaryKey": false,
          "notNull": true,
          "autoincrement": false
        },
        "currency": {
          "name": "currency",
          "type": "varchar(3)",
          "primaryKey": false,
          "notNull": true,
          "autoincrement": false,
          "default": "'USD'"
        },
        "stripe_session_id": {
          "name": "stripe_session_id",
          "type": "varchar(255)",
          "primaryKey": false,
          "notNull": false,
          "autoincrement": false
        },
        "stripe_payment_intent_id": {
          "name": "stripe_payment_intent_id",
          "type": "varchar(255)",
          "primaryKey": false,
          "notNull": false,
          "autoincrement": false
        },
        "invoice_pdf_url": {
          "name": "invoice_pdf_url",
          "type": "text",
          "primaryKey": false,
          "notNull": false,
          "autoincrement": false
        },
        "invoice_pdf_key": {
          "name": "invoice_pdf_key",
          "type": "text",
          "primaryKey": false,
          "notNull": false,
          "autoincrement": false
        },
        "created_at": {
          "name": "created_at",
          "type": "timestamp",
          "primaryKey": false,
          "notNull": true,
          "autoincrement": false,
          "default": "(now())"
        },
        "paid_at": {
          "name": "paid_at",
          "type": "timestamp",
          "primaryKey": false,
          "notNull": false,
          "autoincrement": false
        }
      },
      "indexes": {},
      "foreignKeys": {
        "orders_user_id_users_id_fk": {
          "name": "orders_user_id_users_id_fk",
          "tableFrom": "orders",
          "tableTo": "users",
          "columnsFrom": [
            "user_id"
          ],
          "columnsTo": [
            "id"
          ],
          "onDelete": "no action",
          "onUpdate": "no action"
        },
        "orders_project_id_projects_id_fk": {
          "name": "orders_project_id_projects_id_fk",
          "tableFrom": "orders",
          "tableTo": "projects",
          "columnsFrom": [
            "project_id"
          ],
          "columnsTo": [
            "id"
          ],
          "onDelete": "no action",
          "onUpdate": "no action"
        }
      },
      "compositePrimaryKeys": {
        "orders_id": {
          "name": "orders_id",
          "columns": [
            "id"
          ]
        }
      },
      "uniqueConstraints": {
        "orders_order_number_unique": {
          "name": "orders_order_number_unique",
          "columns": [
            "order_number"
          ]
        },
        "orders_invoice_number_unique": {
          "name": "orders_invoice_number_unique",
          "columns": [
            "invoice_number"
          ]
        }
      },
      "checkConstraint": {}
    },
    "portfolioItems": {
      "name": "portfolioItems",
      "columns": {
        "id": {
          "name": "id",
          "type": "int",
          "primaryKey": false,
          "notNull": true,
          "autoincrement": true
        },
        "title": {
          "name": "title",
          "type": "varchar(255)",
          "primaryKey": false,
          "notNull": true,
          "autoincrement": false
        },
        "description": {
          "name": "description",
          "type": "text",
          "primaryKey": false,
          "notNull": false,
          "autoincrement": false
        },
        "imageUrl": {
          "name": "imageUrl",
          "type": "varchar(500)",
          "primaryKey": false,
          "notNull": true,
          "autoincrement": false
        },
        "category": {
          "name": "category",
          "type": "varchar(100)",
          "primaryKey": false,
          "notNull": false,
          "autoincrement": false
        },
        "featured": {
          "name": "featured",
          "type": "int",
          "primaryKey": false,
          "notNull": true,
          "autoincrement": false,
          "default": 0
        },
        "displayOrder": {
          "name": "displayOrder",
          "type": "int",
          "primaryKey": false,
          "notNull": true,
          "autoincrement": false,
          "default": 0
        },
        "createdAt": {
          "name": "createdAt",
          "type": "timestamp",
          "primaryKey": false,
          "notNull": true,
          "autoincrement": false,
          "default": "(now())"
        }
      },
      "indexes": {},
      "foreignKeys": {},
      "compositePrimaryKeys": {
        "portfolioItems_id": {
          "name": "portfolioItems_id",
          "columns": [
            "id"
          ]
        }
      },
      "uniqueConstraints": {},
      "checkConstraint": {}
    },
    "product_pricing_tiers": {
      "name": "product_pricing_tiers",
      "columns": {
        "id": {
          "name": "id",
          "type": "int",
          "primaryKey": false,
          "notNull": true,
          "autoincrement": true
        },
        "product_id": {
          "name": "product_id",
          "type": "int",
          "primaryKey": false,
          "notNull": true,
          "autoincrement": false
        },
        "min_quantity": {
          "name": "min_quantity",
          "type": "int",
          "primaryKey": false,
          "notNull": true,
          "autoincrement": false
        },
        "max_quantity": {
          "name": "max_quantity",
          "type": "int",
          "primaryKey": false,
          "notNull": false,
          "autoincrement": false
        },
        "price_per_unit": {
          "name": "price_per_unit",
          "type": "int",
          "primaryKey": false,
          "notNull": true,
          "autoincrement": false
        },
        "created_at": {
          "name": "created_at",
          "type": "timestamp",
          "primaryKey": false,
          "notNull": true,
          "autoincrement": false,
          "default": "(now())"
        }
      },
      "indexes": {},
      "foreignKeys": {
        "product_pricing_tiers_product_id_catalog_products_id_fk": {
          "name": "product_pricing_tiers_product_id_catalog_products_id_fk",
          "tableFrom": "product_pricing_tiers",
          "tableTo": "catalog_products",
          "columnsFrom": [
            "product_id"
          ],
          "columnsTo": [
            "id"
          ],
          "onDelete": "cascade",
          "onUpdate": "no action"
        }
      },
      "compositePrimaryKeys": {
        "product_pricing_tiers_id": {
          "name": "product_pricing_tiers_id",
          "columns": [
            "id"
          ]
        }
      },
      "uniqueConstraints": {},
      "checkConstraint": {}
    },
    "productionSetups": {
      "name": "productionSetups",
      "columns": {
        "id": {
          "name": "id",
          "type": "int",
          "primaryKey": false,
          "notNull": true,
          "autoincrement": true
        },
        "projectId": {
          "name": "projectId",
          "type": "int",
          "primaryKey": false,
          "notNull": true,
          "autoincrement": false
        },
        "checklist": {
          "name": "checklist",
          "type": "text",
          "primaryKey": false,
          "notNull": false,
          "autoincrement": false
        },
        "engraverSettings": {
          "name": "engraverSettings",
          "type": "text",
          "primaryKey": false,
          "notNull": false,
          "autoincrement": false
        },
        "packagingSetup": {
          "name": "packagingSetup",
          "type": "text",
          "primaryKey": false,
          "notNull": false,
          "autoincrement": false
        },
        "materialsPrepared": {
          "name": "materialsPrepared",
          "type": "int",
          "primaryKey": false,
          "notNull": true,
          "autoincrement": false,
          "default": 0
        },
        "estimatedCompletionDate": {
          "name": "estimatedCompletionDate",
          "type": "timestamp",
          "primaryKey": false,
          "notNull": false,
          "autoincrement": false
        },
        "notes": {
          "name": "notes",
          "type": "text",
          "primaryKey": false,
          "notNull": false,
          "autoincrement": false
        },
        "createdAt": {
          "name": "createdAt",
          "type": "timestamp",
          "primaryKey": false,
          "notNull": true,
          "autoincrement": false,
          "default": "(now())"
        },
        "updatedAt": {
          "name": "updatedAt",
          "type": "timestamp",
          "primaryKey": false,
          "notNull": true,
          "autoincrement": false,
          "onUpdate": true,
          "default": "(now())"
        }
      },
      "indexes": {},
      "foreignKeys": {},
      "compositePrimaryKeys": {
        "productionSetups_id": {
          "name": "productionSetups_id",
          "columns": [
            "id"
          ]
        }
      },
      "uniqueConstraints": {},
      "checkConstraint": {}
    },
    "project_messages": {
      "name": "project_messages",
      "columns": {
        "id": {
          "name": "id",
          "type": "int",
          "primaryKey": false,
          "notNull": true,
          "autoincrement": true
        },
        "project_id": {
          "name": "project_id",
          "type": "int",
          "primaryKey": false,
          "notNull": true,
          "autoincrement": false
        },
        "sender_id": {
          "name": "sender_id",
          "type": "int",
          "primaryKey": false,
          "notNull": true,
          "autoincrement": false
        },
        "sender_name": {
          "name": "sender_name",
          "type": "varchar(255)",
          "primaryKey": false,
          "notNull": true,
          "autoincrement": false
        },
        "sender_role": {
          "name": "sender_role",
          "type": "enum('admin','user')",
          "primaryKey": false,
          "notNull": true,
          "autoincrement": false
        },
        "message": {
          "name": "message",
          "type": "text",
          "primaryKey": false,
          "notNull": true,
          "autoincrement": false
        },
        "created_at": {
          "name": "created_at",
          "type": "timestamp",
          "primaryKey": false,
          "notNull": true,
          "autoincrement": false,
          "default": "(now())"
        }
      },
      "indexes": {},
      "foreignKeys": {
        "project_messages_project_id_projects_id_fk": {
          "name": "project_messages_project_id_projects_id_fk",
          "tableFrom": "project_messages",
          "tableTo": "projects",
          "columnsFrom": [
            "project_id"
          ],
          "columnsTo": [
            "id"
          ],
          "onDelete": "cascade",
          "onUpdate": "no action"
        }
      },
      "compositePrimaryKeys": {
        "project_messages_id": {
          "name": "project_messages_id",
          "columns": [
            "id"
          ]
        }
      },
      "uniqueConstraints": {},
      "checkConstraint": {}
    },
    "projects": {
      "name": "projects",
      "columns": {
        "id": {
          "name": "id",
          "type": "int",
          "primaryKey": false,
          "notNull": true,
          "autoincrement": true
        },
        "clientName": {
          "name": "clientName",
          "type": "varchar(255)",
          "primaryKey": false,
          "notNull": true,
          "autoincrement": false
        },
        "clientEmail": {
          "name": "clientEmail",
          "type": "varchar(320)",
          "primaryKey": false,
          "notNull": true,
          "autoincrement": false
        },
        "clientPhone": {
          "name": "clientPhone",
          "type": "varchar(50)",
          "primaryKey": false,
          "notNull": false,
          "autoincrement": false
        },
        "projectTitle": {
          "name": "projectTitle",
          "type": "varchar(255)",
          "primaryKey": false,
          "notNull": true,
          "autoincrement": false
        },
        "status": {
          "name": "status",
          "type": "enum('intake','design','approval','production','fulfillment','completed','cancelled')",
          "primaryKey": false,
          "notNull": true,
          "autoincrement": false,
          "default": "'intake'"
        },
        "createdAt": {
          "name": "createdAt",
          "type": "timestamp",
          "primaryKey": false,
          "notNull": true,
          "autoincrement": false,
          "default": "(now())"
        },
        "updatedAt": {
          "name": "updatedAt",
          "type": "timestamp",
          "primaryKey": false,
          "notNull": true,
          "autoincrement": false,
          "onUpdate": true,
          "default": "(now())"
        }
      },
      "indexes": {},
      "foreignKeys": {},
      "compositePrimaryKeys": {
        "projects_id": {
          "name": "projects_id",
          "columns": [
            "id"
          ]
        }
      },
      "uniqueConstraints": {},
      "checkConstraint": {}
    },
    "quote_templates": {
      "name": "quote_templates",
      "columns": {
        "id": {
          "name": "id",
          "type": "int",
          "primaryKey": false,
          "notNull": true,
          "autoincrement": true
        },
        "name": {
          "name": "name",
          "type": "varchar(255)",
          "primaryKey": false,
          "notNull": true,
          "autoincrement": false
        },
        "description": {
          "name": "description",
          "type": "text",
          "primaryKey": false,
          "notNull": false,
          "autoincrement": false
        },
        "category": {
          "name": "category",
          "type": "varchar(100)",
          "primaryKey": false,
          "notNull": false,
          "autoincrement": false
        },
        "base_price": {
          "name": "base_price",
          "type": "int",
          "primaryKey": false,
          "notNull": true,
          "autoincrement": false
        },
        "labor_hours": {
          "name": "labor_hours",
          "type": "int",
          "primaryKey": false,
          "notNull": false,
          "autoincrement": false,
          "default": 0
        },
        "hourly_rate": {
          "name": "hourly_rate",
          "type": "int",
          "primaryKey": false,
          "notNull": false,
          "autoincrement": false,
          "default": 0
        },
        "material_cost": {
          "name": "material_cost",
          "type": "int",
          "primaryKey": false,
          "notNull": false,
          "autoincrement": false,
          "default": 0
        },
        "markup_percentage": {
          "name": "markup_percentage",
          "type": "int",
          "primaryKey": false,
          "notNull": false,
          "autoincrement": false,
          "default": 0
        },
        "notes": {
          "name": "notes",
          "type": "text",
          "primaryKey": false,
          "notNull": false,
          "autoincrement": false
        },
        "is_active": {
          "name": "is_active",
          "type": "int",
          "primaryKey": false,
          "notNull": true,
          "autoincrement": false,
          "default": 1
        },
        "created_at": {
          "name": "created_at",
          "type": "timestamp",
          "primaryKey": false,
          "notNull": true,
          "autoincrement": false,
          "default": "(now())"
        },
        "updated_at": {
          "name": "updated_at",
          "type": "timestamp",
          "primaryKey": false,
          "notNull": true,
          "autoincrement": false,
          "onUpdate": true,
          "default": "(now())"
        }
      },
      "indexes": {},
      "foreignKeys": {},
      "compositePrimaryKeys": {
        "quote_templates_id": {
          "name": "quote_templates_id",
          "columns": [
            "id"
          ]
        }
      },
      "uniqueConstraints": {},
      "checkConstraint": {}
    },
    "quotes": {
      "name": "quotes",
      "columns": {
        "id": {
          "name": "id",
          "type": "int",
          "primaryKey": false,
          "notNull": true,
          "autoincrement": true
        },
        "projectId": {
          "name": "projectId",
          "type": "int",
          "primaryKey": false,
          "notNull": true,
          "autoincrement": false
        },
        "amount": {
          "name": "amount",
          "type": "int",
          "primaryKey": false,
          "notNull": true,
          "autoincrement": false
        },
        "currency": {
          "name": "currency",
          "type": "varchar(3)",
          "primaryKey": false,
          "notNull": true,
          "autoincrement": false,
          "default": "'USD'"
        },
        "breakdown": {
          "name": "breakdown",
          "type": "text",
          "primaryKey": false,
          "notNull": false,
          "autoincrement": false
        },
        "clarifyingQuestions": {
          "name": "clarifyingQuestions",
          "type": "text",
          "primaryKey": false,
          "notNull": false,
          "autoincrement": false
        },
        "estimatedDuration": {
          "name": "estimatedDuration",
          "type": "varchar(100)",
          "primaryKey": false,
          "notNull": false,
          "autoincrement": false
        },
        "validUntil": {
          "name": "validUntil",
          "type": "timestamp",
          "primaryKey": false,
          "notNull": false,
          "autoincrement": false
        },
        "status": {
          "name": "status",
          "type": "enum('draft','sent','approved','rejected')",
          "primaryKey": false,
          "notNull": true,
          "autoincrement": false,
          "default": "'draft'"
        },
        "createdAt": {
          "name": "createdAt",
          "type": "timestamp",
          "primaryKey": false,
          "notNull": true,
          "autoincrement": false,
          "default": "(now())"
        },
        "updatedAt": {
          "name": "updatedAt",
          "type": "timestamp",
          "primaryKey": false,
          "notNull": true,
          "autoincrement": false,
          "onUpdate": true,
          "default": "(now())"
        }
      },
      "indexes": {},
      "foreignKeys": {},
      "compositePrimaryKeys": {
        "quotes_id": {
          "name": "quotes_id",
          "columns": [
            "id"
          ]
        }
      },
      "uniqueConstraints": {},
      "checkConstraint": {}
    },
    "statusUpdates": {
      "name": "statusUpdates",
      "columns": {
        "id": {
          "name": "id",
          "type": "int",
          "primaryKey": false,
          "notNull": true,
          "autoincrement": true
        },
        "projectId": {
          "name": "projectId",
          "type": "int",
          "primaryKey": false,
          "notNull": true,
          "autoincrement": false
        },
        "updateType": {
          "name": "updateType",
          "type": "enum('status','approval','inquiry','upsell')",
          "primaryKey": false,
          "notNull": true,
          "autoincrement": false
        },
        "message": {
          "name": "message",
          "type": "text",
          "primaryKey": false,
          "notNull": true,
          "autoincrement": false
        },
        "nextSteps": {
          "name": "nextSteps",
          "type": "text",
          "primaryKey": false,
          "notNull": false,
          "autoincrement": false
        },
        "sentBy": {
          "name": "sentBy",
          "type": "int",
          "primaryKey": false,
          "notNull": true,
          "autoincrement": false
        },
        "createdAt": {
          "name": "createdAt",
          "type": "timestamp",
          "primaryKey": false,
          "notNull": true,
          "autoincrement": false,
          "default": "(now())"
        }
      },
      "indexes": {},
      "foreignKeys": {},
      "compositePrimaryKeys": {
        "statusUpdates_id": {
          "name": "statusUpdates_id",
          "columns": [
            "id"
          ]
        }
      },
      "uniqueConstraints": {},
      "checkConstraint": {}
    },
    "users": {
      "name": "users",
      "columns": {
        "id": {
          "name": "id",
          "type": "int",
          "primaryKey": false,
          "notNull": true,
          "autoincrement": true
        },
        "email": {
          "name": "email",
          "type": "varchar(320)",
          "primaryKey": false,
          "notNull": true,
          "autoincrement": false
        },
        "emailVerified": {
          "name": "emailVerified",
          "type": "int",
          "primaryKey": false,
          "notNull": true,
          "autoincrement": false,
          "default": 0
        },
        "name": {
          "name": "name",
          "type": "text",
          "primaryKey": false,
          "notNull": false,
          "autoincrement": false
        },
        "avatarUrl": {
          "name": "avatarUrl",
          "type": "varchar(500)",
          "primaryKey": false,
          "notNull": false,
          "autoincrement": false
        },
        "role": {
          "name": "role",
          "type": "enum('user','admin')",
          "primaryKey": false,
          "notNull": true,
          "autoincrement": false,
          "default": "'user'"
        },
        "createdAt": {
          "name": "createdAt",
          "type": "timestamp",
          "primaryKey": false,
          "notNull": true,
          "autoincrement": false,
          "default": "(now())"
        },
        "updatedAt": {
          "name": "updatedAt",
          "type": "timestamp",
          "primaryKey": false,
          "notNull": true,
          "autoincrement": false,
          "onUpdate": true,
          "default": "(now())"
        },
        "lastSignedIn": {
          "name": "lastSignedIn",
          "type": "timestamp",
          "primaryKey": false,
          "notNull": true,
          "autoincrement": false,
          "default": "(now())"
        }
      },
      "indexes": {},
      "foreignKeys": {},
      "compositePrimaryKeys": {
        "users_id": {
          "name": "users_id",
          "columns": [
            "id"
          ]
        }
      },
      "uniqueConstraints": {
        "users_email_unique": {
          "name": "users_email_unique",
          "columns": [
            "email"
          ]
        }
      },
      "checkConstraint": {}
    },
    "oauth_accounts": {
      "name": "oauth_accounts",
      "columns": {
        "id": {
          "name": "id",
          "type": "int",
          "primaryKey": false,
          "notNull": true,
          "autoincrement": true
        },
        "user_id": {
          "name": "user_id",
          "type": "int",
          "primaryKey": false,
          "notNull": true,
          "autoincrement": false
        },
        "provider": {
          "name": "provider",
          "type": "varchar(50)",
          "primaryKey": false,
          "notNull": true,
          "autoincrement": false
        },
        "provider_account_id": {
          "name": "provider_account_id",
          "type": "varchar(255)",
          "primaryKey": false,
          "notNull": true,
          "autoincrement": false
        },
        "access_token": {
          "name": "access_token",
          "type": "text",
          "primaryKey": false,
          "notNull": false,
          "autoincrement": false
        },
        "refresh_token": {
          "name": "refresh_token",
          "type": "text",
          "primaryKey": false,
          "notNull": false,
          "autoincrement": false
        },
        "expires_at": {
          "name": "expires_at",
          "type": "timestamp",
          "primaryKey": false,
          "notNull": false,
          "autoincrement": false
        },
        "created_at": {
          "name": "created_at",
          "type": "timestamp",
          "primaryKey": false,
          "notNull": true,
          "autoincrement": false,
          "default": "(now())"
        }
      },
      "indexes": {},
      "foreignKeys": {},
      "compositePrimaryKeys": {
        "oauth_accounts_id": {
          "name": "oauth_accounts_id",
          "columns": [
            "id"
          ]
        }
      },
      "uniqueConstraints": {},
      "checkConstraint": {}
    },
    "passwords": {
      "name": "passwords",
      "columns": {
        "user_id": {
          "name": "user_id",
          "type": "int",
          "primaryKey": false,
          "notNull": true,
          "autoincrement": false
        },
        "hashed_password": {
          "name": "hashed_password",
          "type": "varchar(255)",
          "primaryKey": false,
          "notNull": true,
          "autoincrement": false
        },
        "updated_at": {
          "name": "updated_at",
          "type": "timestamp",
          "primaryKey": false,
          "notNull": true,
          "autoincrement": false,
          "onUpdate": true,
          "default": "(now())"
        }
      },
      "indexes": {},
      "foreignKeys": {},
      "compositePrimaryKeys": {
        "passwords_user_id": {
          "name": "passwords_user_id",
          "columns": [
            "user_id"
          ]
        }
      },
      "uniqueConstraints": {},
      "checkConstraint": {}
    },
    "sessions": {
      "name": "sessions",
      "columns": {
        "id": {
          "name": "id",
          "type": "varchar(255)",
          "primaryKey": false,
          "notNull": true,
          "autoincrement": false
        },
        "user_id": {
          "name": "user_id",
          "type": "int",
          "primaryKey": false,
          "notNull": true,
          "autoincrement": false
        },
        "expires_at": {
          "name": "expires_at",
          "type": "timestamp",
          "primaryKey": false,
          "notNull": true,
          "autoincrement": false
        },
        "created_at": {
          "name": "created_at",
          "type": "timestamp",
          "primaryKey": false,
          "notNull": true,
          "autoincrement": false,
          "default": "(now())"
        }
      },
      "indexes": {},
      "foreignKeys": {},
      "compositePrimaryKeys": {
        "sessions_id": {
          "name": "sessions_id",
          "columns": [
            "id"
          ]
        }
      },
      "uniqueConstraints": {},
      "checkConstraint": {}
    }
  },
  "views": {},
  "_meta": {
    "schemas": {},
    "tables": {},
    "columns": {
      "\"project_messages\".\"sender_open_id\"": "\"project_messages\".\"sender_id\""
    }
  },
  "internal": {
    "tables": {},
    "indexes": {}
  }
}